bx_py_utils/__init__.py
bx_py_utils/anonymize.py
bx_py_utils/auto_doc.py
bx_py_utils/compat.py
bx_py_utils/dict_utils.py
bx_py_utils/environ.py
bx_py_utils/error_handling.py
bx_py_utils/file_utils.py
bx_py_utils/filename_matcher.py
bx_py_utils/graphql_introspection.py
bx_py_utils/hash_utils.py
bx_py_utils/html_utils.py
bx_py_utils/import_utils.py
bx_py_utils/iteration.py
bx_py_utils/path.py
bx_py_utils/processify.py
bx_py_utils/pyproject_toml.py
bx_py_utils/rison.py
bx_py_utils/stack_info.py
bx_py_utils/string_utils.py
bx_py_utils/text_tools.py
bx_py_utils/aws/__init__.py
bx_py_utils/aws/client_side_cert_manager.py
bx_py_utils/aws/secret_manager.py
bx_py_utils/doc_write/README.md
bx_py_utils/doc_write/__init__.py
bx_py_utils/doc_write/__main__.py
bx_py_utils/doc_write/api.py
bx_py_utils/doc_write/cfg.py
bx_py_utils/doc_write/data_structures.py
bx_py_utils/doc_write/docstrings.py
bx_py_utils/doc_write/macro.py
bx_py_utils/doc_write/walk.py
bx_py_utils/humanize/__init__.py
bx_py_utils/humanize/pformat.py
bx_py_utils/humanize/time.py
bx_py_utils/test_utils/__init__.py
bx_py_utils/test_utils/assertion.py
bx_py_utils/test_utils/context_managers.py
bx_py_utils/test_utils/datetime.py
bx_py_utils/test_utils/deny_requests.py
bx_py_utils/test_utils/filesystem_utils.py
bx_py_utils/test_utils/log_utils.py
bx_py_utils/test_utils/mock_aws_secret_manager.py
bx_py_utils/test_utils/mock_boto3session.py
bx_py_utils/test_utils/mock_uuid.py
bx_py_utils/test_utils/mocks3.py
bx_py_utils/test_utils/redirect.py
bx_py_utils/test_utils/requests_mock_assertion.py
bx_py_utils/test_utils/snapshot.py
bx_py_utils/test_utils/time.py
bx_py_utils/test_utils/unittest_utils.py
bx_py_utils/test_utils/xlsx.py
bx_py_utils/test_utils/zip_file_utils.py
bx_py_utils-113.dist-info/METADATA
bx_py_utils-113.dist-info/WHEEL
bx_py_utils-113.dist-info/entry_points.txt
bx_py_utils-113.dist-info/licenses/LICENSE
bx_py_utils-113.dist-info/RECORD
