Metadata-Version: 2.4
Name: bx_py_utils
Version: 113
Summary: Various Python utility functions
Project-URL: Documentation, https://github.com/boxine/bx_py_utils/
Project-URL: Source, https://github.com/boxine/bx_py_utils/
Author-email: Jens Diemer <jens.diemer@boxine.de>, Philipp Hagemeister <phihag@phihag.de>, Florian Braun <mail@chiron-online.de>, Christian Schneider <christian@cnschn.com>
License: MIT
License-File: LICENSE
Keywords: utilities
Classifier: Development Status :: 5 - Production/Stable
Classifier: Intended Audience :: Developers
Classifier: Programming Language :: Python :: 3 :: Only
Classifier: Programming Language :: Python :: 3.10
Classifier: Programming Language :: Python :: 3.11
Classifier: Programming Language :: Python :: 3.12
Classifier: Programming Language :: Python :: 3.13
Classifier: Topic :: Software Development :: Libraries :: Python Modules
Requires-Python: <4,>=3.10
